LICENSE.txt
MANIFEST.in
README.rst
setup.py
cmsplugin_disqus/__init__.py
cmsplugin_disqus/cms_plugins.py
cmsplugin_disqus/models.py
cmsplugin_disqus.egg-info/PKG-INFO
cmsplugin_disqus.egg-info/SOURCES.txt
cmsplugin_disqus.egg-info/dependency_links.txt
cmsplugin_disqus.egg-info/not-zip-safe
cmsplugin_disqus.egg-info/requires.txt
cmsplugin_disqus.egg-info/top_level.txt
cmsplugin_disqus/locale/de/LC_MESSAGES/django.mo
cmsplugin_disqus/locale/de/LC_MESSAGES/django.po
cmsplugin_disqus/locale/en/LC_MESSAGES/django.mo
cmsplugin_disqus/locale/en/LC_MESSAGES/django.po
cmsplugin_disqus/locale/fr/LC_MESSAGES/django.mo
cmsplugin_disqus/locale/fr/LC_MESSAGES/django.po
cmsplugin_disqus/locale/it/LC_MESSAGES/django.mo
cmsplugin_disqus/locale/it/LC_MESSAGES/django.po
cmsplugin_disqus/locale/ja/LC_MESSAGES/django.mo
cmsplugin_disqus/locale/ja/LC_MESSAGES/django.po
cmsplugin_disqus/migrations/0001_initial.py
cmsplugin_disqus/migrations/__init__.py
cmsplugin_disqus/templates/cmsplugin_disqus/disqus_plugin.html